{
	"description": "Project configuration file",
	"packOptions": {
		"ignore": []
	},
	"setting": {
		"urlCheck": false,
		"es6": true,
		"postcss": true,
		"minified": true,
		"newFeature": true,
		"coverView": true,
		"autoAudits": false,
		"checkInvalidKey": true,
		"checkSiteMap": true,
		"uploadWithSourceMap": true,
		"babelSetting": {
			"ignore": [],
			"disablePlugins": [],
			"outputPath": ""
		}
	},
	"compileType": "miniprogram",
	"libVersion": "2.7.7",
	"appid": "wxb6357d36b03313c4",
	"projectname": "tingbudong",
	"debugOptions": {
		"hidedInDevtools": []
	},
	"isGameTourist": false,
	"simulatorType": "wechat",
	"simulatorPluginLibVersion": {},
	"condition": {
		"search": {
			"current": -1,
			"list": []
		},
		"conversation": {
			"current": -1,
			"list": []
		},
		"plugin": {
			"current": -1,
			"list": []
		},
		"game": {
			"currentL": -1,
			"list": []
		},
		"miniprogram": {
			"current": 1,
			"list": [
				{
					"id": 1,
					"name": "Index page",
					"pathName": "pages/index/index",
					"query": "",
					"scene": null
				},
				{
					"id": 1,
					"name": "Show page",
					"pathName": "pages/show/show",
					"query": "",
					"scene": null
				},
				{
					"id": 3,
					"name": "New Slang",
					"pathName": "pages/form/form",
					"query": "",
					"scene": null
				},
				{
					"id": 4,
					"name": "Edit definition",
					"pathName": "pages/editDefinition/editDefinition",
					"query": "",
					"scene": null
				},
				{
					"id": 5,
					"name": "Edit Slang",
					"pathName": "pages/editSlang/editSlang",
					"query": "",
					"scene": null
				},
				{
					"id": 6,
					"name": "pages/addDef/addDef",
					"pathName": "pages/addDef/addDef",
					"query": "",
					"scene": null
				},
				{
					"id": 7,
					"name": "Profile",
					"pathName": "pages/profile/profile",
					"query": "",
					"scene": null
				}
			]
		}
	}
}